datalogue/__init__.py
datalogue/credentials.py
datalogue/dtl.py
datalogue/dtl_utils.py
datalogue/errors.py
datalogue/version.py
datalogue/anduin/__init__.py
datalogue/anduin/client.py
datalogue/anduin/models/__init__.py
datalogue/anduin/models/datastore.py
datalogue/anduin/models/stream.py
datalogue/auth/__init__.py
datalogue/auth/authentication.py
datalogue/clients/__init__.py
datalogue/clients/authentication.py
datalogue/clients/automation.py
datalogue/clients/classifier.py
datalogue/clients/credentials.py
datalogue/clients/datastore.py
datalogue/clients/datastore_collections.py
datalogue/clients/group.py
datalogue/clients/http.py
datalogue/clients/jobs.py
datalogue/clients/ml.py
datalogue/clients/ontology.py
datalogue/clients/organization.py
datalogue/clients/pipeline.py
datalogue/clients/processed_sources.py
datalogue/clients/regex.py
datalogue/clients/tag.py
datalogue/clients/test_auth_client.py
datalogue/clients/user.py
datalogue/models/__init__.py
datalogue/models/classifier.py
datalogue/models/credentials.py
datalogue/models/datastore.py
datalogue/models/datastore_collection.py
datalogue/models/graph.py
datalogue/models/job.py
datalogue/models/metrics.py
datalogue/models/model.py
datalogue/models/ontology.py
datalogue/models/organization.py
datalogue/models/permission.py
datalogue/models/pipeline.py
datalogue/models/pipeline_behavior.py
datalogue/models/pipeline_template.py
datalogue/models/regex.py
datalogue/models/s3encryption.py
datalogue/models/schema.py
datalogue/models/scope_level.py
datalogue/models/tag.py
datalogue/models/version.py
datalogue/models/kinesis/__init__.py
datalogue/models/kinesis/shards.py
datalogue/models/transformations/__init__.py
datalogue/models/transformations/add.py
datalogue/models/transformations/append_index_to_label.py
datalogue/models/transformations/casts.py
datalogue/models/transformations/classify.py
datalogue/models/transformations/commons.py
datalogue-0.39.0.dist-info/DESCRIPTION.rst
datalogue-0.39.0.dist-info/METADATA
datalogue-0.39.0.dist-info/RECORD
datalogue-0.39.0.dist-info/WHEEL
datalogue-0.39.0.dist-info/metadata.json
datalogue-0.39.0.dist-info/top_level.txt
