Metadata-Version: 2.0
Name: datalogue
Version: 0.39.0
Summary: SDK to interact with the datalogue platform
Home-page: https://github.com/datalogue/dtl-python-sdk
Author: Nicolas Joseph
Author-email: nic@datalogue.io
License: Copyright 2019 Datalogue, Inc.
Requires-Dist: numpy
Requires-Dist: pandas
Requires-Dist: pbkdf2
Requires-Dist: pyarrow
Requires-Dist: pytest (==3.6.3)
Requires-Dist: python-dateutil
Requires-Dist: pyyaml
Requires-Dist: requests
Requires-Dist: validators
